pyquential/__init__.py
pyquential/extensions.py
pyquential-0.0.3.dist-info/LICENSE
pyquential-0.0.3.dist-info/METADATA
pyquential-0.0.3.dist-info/WHEEL
pyquential-0.0.3.dist-info/top_level.txt
pyquential-0.0.3.dist-info/RECORD
