Metadata-Version: 2.1
Name: pyquential
Version: 0.0.3
Summary: Extension functions for iterables to ease functional programming.
Home-page: https://github.com/kevin-winter/pyquential
Author: Kevin Winter
Author-email: kevin.n.winter@gmail.com
License: MIT
Platform: UNKNOWN
Requires-Dist: numpy
Requires-Dist: pandas
Requires-Dist: pyfunctional
Requires-Dist: forbiddenfruit
